eml/__init__.py
eml/util.py
eml/backend/__init__.py
eml/backend/base.py
eml/backend/cplex_backend.py
eml/backend/ortool_backend.py
eml/net/__init__.py
eml/net/describe.py
eml/net/embed.py
eml/net/process.py
eml/net/reader/__init__.py
eml/net/reader/keras_reader.py
eml/tree/__init__.py
eml/tree/describe.py
eml/tree/embed.py
eml/tree/process.py
eml/tree/reader/__init__.py
eml/tree/reader/sklearn_reader.py
examples/__init__.py
examples/cplex_example_regression.py
examples/ortools_example_regression.py
emllib-1.0.2.dist-info/METADATA
emllib-1.0.2.dist-info/WHEEL
emllib-1.0.2.dist-info/top_level.txt
emllib-1.0.2.dist-info/RECORD
