Metadata-Version: 2.1
Name: emllib
Version: 1.0.2
Summary: Library fro Empirical Model Learning 
Home-page: https://github.com/emlopt/emllib
Author: University of Bologna - DISI
Maintainer: Federico Baldo
Maintainer-email: federico.baldo2@unibo.it
License: UNKNOWN
Platform: UNKNOWN
Requires-Python: >=3.6
